{
    "family": "emulador-task",
    "executionRoleArn": "arn:aws:iam::924609080348:role/ecsTaskExecutionRole",
    "taskRoleArn": "arn:aws:iam::924609080348:role/ecsTaskRole",
    "containerDefinitions": [
        {
            "name": "error_emulator",
            "image": "...",
            "cpu": 256,
            "memory": 512,
            "essential": true
        }
    ],
    "requiresCompatibilities": [
        "FARGATE"
    ],
    "networkMode": "awsvpc",
    "cpu": "256",
    "memory": "512"
}